callme/__init.py__.py
callme/main.py
callme_marck-6.8.0.dist-info/METADATA
callme_marck-6.8.0.dist-info/WHEEL
callme_marck-6.8.0.dist-info/top_level.txt
callme_marck-6.8.0.dist-info/RECORD
